{"url":"https:\/\/api.github.com\/repos\/octocat\/Spoon-Knife\/pulls\/15363","id":173676995,"html_url":"https:\/\/github.com\/octocat\/Spoon-Knife\/pull\/15363","diff_url":"https:\/\/github.com\/octocat\/Spoon-Knife\/pull\/15363.diff","patch_url":"https:\/\/github.com\/octocat\/Spoon-Knife\/pull\/15363.patch","issue_url":"https:\/\/api.github.com\/repos\/octocat\/Spoon-Knife\/issues\/15363","number":15363,"state":"open","locked":false,"title":"Added paragraph","user":{"login":"codecobber","id":17332869,"avatar_url":"https:\/\/avatars0.githubusercontent.com\/u\/17332869?v=4","gravatar_id":"","url":"https:\/\/api.github.com\/users\/codecobber","html_url":"https:\/\/github.com\/codecobber","followers_url":"https:\/\/api.github.com\/users\/codecobber\/followers","following_url":"https:\/\/api.github.com\/users\/codecobber\/following{\/other_user}","gists_url":"https:\/\/api.github.com\/users\/codecobber\/gists{\/gist_id}","starred_url":"https:\/\/api.github.com\/users\/codecobber\/starred{\/owner}{\/repo}","subscriptions_url":"https:\/\/api.github.com\/users\/codecobber\/subscriptions","organizations_url":"https:\/\/api.github.com\/users\/codecobber\/orgs","repos_url":"https:\/\/api.github.com\/users\/codecobber\/repos","events_url":"https:\/\/api.github.com\/users\/codecobber\/events{\/privacy}","received_events_url":"https:\/\/api.github.com\/users\/codecobber\/received_events","type":"User","site_admin":false},"body":"Just a quick test","created_at":"2018-03-08T08:50:04Z","updated_at":"2018-03-08T09:08:42Z","closed_at":null,"merged_at":null,"merge_commit_sha":"73b6ffb01ee1628b79aa3dc9e6c7dae1da34ef64","assignee":null,"assignees":[],"requested_reviewers":[],"requested_teams":[],"labels":[],"milestone":null,"commits_url":"https:\/\/api.github.com\/repos\/octocat\/Spoon-Knife\/pulls\/15363\/commits","review_comments_url":"https:\/\/api.github.com\/repos\/octocat\/Spoon-Knife\/pulls\/15363\/comments","review_comment_url":"https:\/\/api.github.com\/repos\/octocat\/Spoon-Knife\/pulls\/comments{\/number}","comments_url":"https:\/\/api.github.com\/repos\/octocat\/Spoon-Knife\/issues\/15363\/comments","statuses_url":"https:\/\/api.github.com\/repos\/octocat\/Spoon-Knife\/statuses\/5051d93e0ca7fb94b61f5faf4f98b9d59d6e9166","head":{"label":"codecobber:master","ref":"master","sha":"5051d93e0ca7fb94b61f5faf4f98b9d59d6e9166","user":{"login":"codecobber","id":17332869,"avatar_url":"https:\/\/avatars0.githubusercontent.com\/u\/17332869?v=4","gravatar_id":"","url":"https:\/\/api.github.com\/users\/codecobber","html_url":"https:\/\/github.com\/codecobber","followers_url":"https:\/\/api.github.com\/users\/codecobber\/followers","following_url":"https:\/\/api.github.com\/users\/codecobber\/following{\/other_user}","gists_url":"https:\/\/api.github.com\/users\/codecobber\/gists{\/gist_id}","starred_url":"https:\/\/api.github.com\/users\/codecobber\/starred{\/owner}{\/repo}","subscriptions_url":"https:\/\/api.github.com\/users\/codecobber\/subscriptions","organizations_url":"https:\/\/api.github.com\/users\/codecobber\/orgs","repos_url":"https:\/\/api.github.com\/users\/codecobber\/repos","events_url":"https:\/\/api.github.com\/users\/codecobber\/events{\/privacy}","received_events_url":"https:\/\/api.github.com\/users\/codecobber\/received_events","type":"User","site_admin":false},"repo":{"id":124361386,"name":"Spoon-Knife","full_name":"codecobber\/Spoon-Knife","owner":{"login":"codecobber","id":17332869,"avatar_url":"https:\/\/avatars0.githubusercontent.com\/u\/17332869?v=4","gravatar_id":"","url":"https:\/\/api.github.com\/users\/codecobber","html_url":"https:\/\/github.com\/codecobber","followers_url":"https:\/\/api.github.com\/users\/codecobber\/followers","following_url":"https:\/\/api.github.com\/users\/codecobber\/following{\/other_user}","gists_url":"https:\/\/api.github.com\/users\/codecobber\/gists{\/gist_id}","starred_url":"https:\/\/api.github.com\/users\/codecobber\/starred{\/owner}{\/repo}","subscriptions_url":"https:\/\/api.github.com\/users\/codecobber\/subscriptions","organizations_url":"https:\/\/api.github.com\/users\/codecobber\/orgs","repos_url":"https:\/\/api.github.com\/users\/codecobber\/repos","events_url":"https:\/\/api.github.com\/users\/codecobber\/events{\/privacy}","received_events_url":"https:\/\/api.github.com\/users\/codecobber\/received_events","type":"User","site_admin":false},"private":false,"html_url":"https:\/\/github.com\/codecobber\/Spoon-Knife","description":"This repo is for demonstration purposes only.","fork":true,"url":"https:\/\/api.github.com\/repos\/codecobber\/Spoon-Knife","forks_url":"https:\/\/api.github.com\/repos\/codecobber\/Spoon-Knife\/forks","keys_url":"https:\/\/api.github.com\/repos\/codecobber\/Spoon-Knife\/keys{\/key_id}","collaborators_url":"https:\/\/api.github.com\/repos\/codecobber\/Spoon-Knife\/collaborators{\/collaborator}","teams_url":"https:\/\/api.github.com\/repos\/codecobber\/Spoon-Knife\/teams","hooks_url":"https:\/\/api.github.com\/repos\/codecobber\/Spoon-Knife\/hooks","issue_events_url":"https:\/\/api.github.com\/repos\/codecobber\/Spoon-Knife\/issues\/events{\/number}","events_url":"https:\/\/api.github.com\/repos\/codecobber\/Spoon-Knife\/events","assignees_url":"https:\/\/api.github.com\/repos\/codecobber\/Spoon-Knife\/assignees{\/user}","branches_url":"https:\/\/api.github.com\/repos\/codecobber\/Spoon-Knife\/branches{\/branch}","tags_url":"https:\/\/api.github.com\/repos\/codecobber\/Spoon-Knife\/tags","blobs_url":"https:\/\/api.github.com\/repos\/codecobber\/Spoon-Knife\/git\/blobs{\/sha}","git_tags_url":"https:\/\/api.github.com\/repos\/codecobber\/Spoon-Knife\/git\/tags{\/sha}","git_refs_url":"https:\/\/api.github.com\/repos\/codecobber\/Spoon-Knife\/git\/refs{\/sha}","trees_url":"https:\/\/api.github.com\/repos\/codecobber\/Spoon-Knife\/git\/trees{\/sha}","statuses_url":"https:\/\/api.github.com\/repos\/codecobber\/Spoon-Knife\/statuses\/{sha}","languages_url":"https:\/\/api.github.com\/repos\/codecobber\/Spoon-Knife\/languages","stargazers_url":"https:\/\/api.github.com\/repos\/codecobber\/Spoon-Knife\/stargazers","contributors_url":"https:\/\/api.github.com\/repos\/codecobber\/Spoon-Knife\/contributors","subscribers_url":"https:\/\/api.github.com\/repos\/codecobber\/Spoon-Knife\/subscribers","subscription_url":"https:\/\/api.github.com\/repos\/codecobber\/Spoon-Knife\/subscription","commits_url":"https:\/\/api.github.com\/repos\/codecobber\/Spoon-Knife\/commits{\/sha}","git_commits_url":"https:\/\/api.github.com\/repos\/codecobber\/Spoon-Knife\/git\/commits{\/sha}","comments_url":"https:\/\/api.github.com\/repos\/codecobber\/Spoon-Knife\/comments{\/number}","issue_comment_url":"https:\/\/api.github.com\/repos\/codecobber\/Spoon-Knife\/issues\/comments{\/number}","contents_url":"https:\/\/api.github.com\/repos\/codecobber\/Spoon-Knife\/contents\/{+path}","compare_url":"https:\/\/api.github.com\/repos\/codecobber\/Spoon-Knife\/compare\/{base}...{head}","merges_url":"https:\/\/api.github.com\/repos\/codecobber\/Spoon-Knife\/merges","archive_url":"https:\/\/api.github.com\/repos\/codecobber\/Spoon-Knife\/{archive_format}{\/ref}","downloads_url":"https:\/\/api.github.com\/repos\/codecobber\/Spoon-Knife\/downloads","issues_url":"https:\/\/api.github.com\/repos\/codecobber\/Spoon-Knife\/issues{\/number}","pulls_url":"https:\/\/api.github.com\/repos\/codecobber\/Spoon-Knife\/pulls{\/number}","milestones_url":"https:\/\/api.github.com\/repos\/codecobber\/Spoon-Knife\/milestones{\/number}","notifications_url":"https:\/\/api.github.com\/repos\/codecobber\/Spoon-Knife\/notifications{?since,all,participating}","labels_url":"https:\/\/api.github.com\/repos\/codecobber\/Spoon-Knife\/labels{\/name}","releases_url":"https:\/\/api.github.com\/repos\/codecobber\/Spoon-Knife\/releases{\/id}","deployments_url":"https:\/\/api.github.com\/repos\/codecobber\/Spoon-Knife\/deployments","created_at":"2018-03-08T08:32:17Z","updated_at":"2018-03-08T08:32:20Z","pushed_at":"2018-03-08T09:06:07Z","git_url":"git:\/\/github.com\/codecobber\/Spoon-Knife.git","ssh_url":"git@github.com:codecobber\/Spoon-Knife.git","clone_url":"https:\/\/github.com\/codecobber\/Spoon-Knife.git","svn_url":"https:\/\/github.com\/codecobber\/Spoon-Knife","homepage":"","size":3,"stargazers_count":0,"watchers_count":0,"language":"HTML","has_issues":false,"has_projects":true,"has_downloads":true,"has_wiki":true,"has_pages":false,"forks_count":0,"mirror_url":null,"archived":false,"open_issues_count":0,"license":null,"forks":0,"open_issues":0,"watchers":0,"default_branch":"master"}},"base":{"label":"octocat:master","ref":"master","sha":"d0dd1f61b33d64e29d8bc1372a94ef6a2fee76a9","user":{"login":"octocat","id":583231,"avatar_url":"https:\/\/avatars3.githubusercontent.com\/u\/583231?v=4","gravatar_id":"","url":"https:\/\/api.github.com\/users\/octocat","html_url":"https:\/\/github.com\/octocat","followers_url":"https:\/\/api.github.com\/users\/octocat\/followers","following_url":"https:\/\/api.github.com\/users\/octocat\/following{\/other_user}","gists_url":"https:\/\/api.github.com\/users\/octocat\/gists{\/gist_id}","starred_url":"https:\/\/api.github.com\/users\/octocat\/starred{\/owner}{\/repo}","subscriptions_url":"https:\/\/api.github.com\/users\/octocat\/subscriptions","organizations_url":"https:\/\/api.github.com\/users\/octocat\/orgs","repos_url":"https:\/\/api.github.com\/users\/octocat\/repos","events_url":"https:\/\/api.github.com\/users\/octocat\/events{\/privacy}","received_events_url":"https:\/\/api.github.com\/users\/octocat\/received_events","type":"User","site_admin":false},"repo":{"id":1300192,"name":"Spoon-Knife","full_name":"octocat\/Spoon-Knife","owner":{"login":"octocat","id":583231,"avatar_url":"https:\/\/avatars3.githubusercontent.com\/u\/583231?v=4","gravatar_id":"","url":"https:\/\/api.github.com\/users\/octocat","html_url":"https:\/\/github.com\/octocat","followers_url":"https:\/\/api.github.com\/users\/octocat\/followers","following_url":"https:\/\/api.github.com\/users\/octocat\/following{\/other_user}","gists_url":"https:\/\/api.github.com\/users\/octocat\/gists{\/gist_id}","starred_url":"https:\/\/api.github.com\/users\/octocat\/starred{\/owner}{\/repo}","subscriptions_url":"https:\/\/api.github.com\/users\/octocat\/subscriptions","organizations_url":"https:\/\/api.github.com\/users\/octocat\/orgs","repos_url":"https:\/\/api.github.com\/users\/octocat\/repos","events_url":"https:\/\/api.github.com\/users\/octocat\/events{\/privacy}","received_events_url":"https:\/\/api.github.com\/users\/octocat\/received_events","type":"User","site_admin":false},"private":false,"html_url":"https:\/\/github.com\/octocat\/Spoon-Knife","description":"This repo is for demonstration purposes only.","fork":false,"url":"https:\/\/api.github.com\/repos\/octocat\/Spoon-Knife","forks_url":"https:\/\/api.github.com\/repos\/octocat\/Spoon-Knife\/forks","keys_url":"https:\/\/api.github.com\/repos\/octocat\/Spoon-Knife\/keys{\/key_id}","collaborators_url":"https:\/\/api.github.com\/repos\/octocat\/Spoon-Knife\/collaborators{\/collaborator}","teams_url":"https:\/\/api.github.com\/repos\/octocat\/Spoon-Knife\/teams","hooks_url":"https:\/\/api.github.com\/repos\/octocat\/Spoon-Knife\/hooks","issue_events_url":"https:\/\/api.github.com\/repos\/octocat\/Spoon-Knife\/issues\/events{\/number}","events_url":"https:\/\/api.github.com\/repos\/octocat\/Spoon-Knife\/events","assignees_url":"https:\/\/api.github.com\/repos\/octocat\/Spoon-Knife\/assignees{\/user}","branches_url":"https:\/\/api.github.com\/repos\/octocat\/Spoon-Knife\/branches{\/branch}","tags_url":"https:\/\/api.github.com\/repos\/octocat\/Spoon-Knife\/tags","blobs_url":"https:\/\/api.github.com\/repos\/octocat\/Spoon-Knife\/git\/blobs{\/sha}","git_tags_url":"https:\/\/api.github.com\/repos\/octocat\/Spoon-Knife\/git\/tags{\/sha}","git_refs_url":"https:\/\/api.github.com\/repos\/octocat\/Spoon-Knife\/git\/refs{\/sha}","trees_url":"https:\/\/api.github.com\/repos\/octocat\/Spoon-Knife\/git\/trees{\/sha}","statuses_url":"https:\/\/api.github.com\/repos\/octocat\/Spoon-Knife\/statuses\/{sha}","languages_url":"https:\/\/api.github.com\/repos\/octocat\/Spoon-Knife\/languages","stargazers_url":"https:\/\/api.github.com\/repos\/octocat\/Spoon-Knife\/stargazers","contributors_url":"https:\/\/api.github.com\/repos\/octocat\/Spoon-Knife\/contributors","subscribers_url":"https:\/\/api.github.com\/repos\/octocat\/Spoon-Knife\/subscribers","subscription_url":"https:\/\/api.github.com\/repos\/octocat\/Spoon-Knife\/subscription","commits_url":"https:\/\/api.github.com\/repos\/octocat\/Spoon-Knife\/commits{\/sha}","git_commits_url":"https:\/\/api.github.com\/repos\/octocat\/Spoon-Knife\/git\/commits{\/sha}","comments_url":"https:\/\/api.github.com\/repos\/octocat\/Spoon-Knife\/comments{\/number}","issue_comment_url":"https:\/\/api.github.com\/repos\/octocat\/Spoon-Knife\/issues\/comments{\/number}","contents_url":"https:\/\/api.github.com\/repos\/octocat\/Spoon-Knife\/contents\/{+path}","compare_url":"https:\/\/api.github.com\/repos\/octocat\/Spoon-Knife\/compare\/{base}...{head}","merges_url":"https:\/\/api.github.com\/repos\/octocat\/Spoon-Knife\/merges","archive_url":"https:\/\/api.github.com\/repos\/octocat\/Spoon-Knife\/{archive_format}{\/ref}","downloads_url":"https:\/\/api.github.com\/repos\/octocat\/Spoon-Knife\/downloads","issues_url":"https:\/\/api.github.com\/repos\/octocat\/Spoon-Knife\/issues{\/number}","pulls_url":"https:\/\/api.github.com\/repos\/octocat\/Spoon-Knife\/pulls{\/number}","milestones_url":"https:\/\/api.github.com\/repos\/octocat\/Spoon-Knife\/milestones{\/number}","notifications_url":"https:\/\/api.github.com\/repos\/octocat\/Spoon-Knife\/notifications{?since,all,participating}","labels_url":"https:\/\/api.github.com\/repos\/octocat\/Spoon-Knife\/labels{\/name}","releases_url":"https:\/\/api.github.com\/repos\/octocat\/Spoon-Knife\/releases{\/id}","deployments_url":"https:\/\/api.github.com\/repos\/octocat\/Spoon-Knife\/deployments","created_at":"2011-01-27T19:30:43Z","updated_at":"2018-03-11T14:22:56Z","pushed_at":"2018-03-11T15:36:09Z","git_url":"git:\/\/github.com\/octocat\/Spoon-Knife.git","ssh_url":"git@github.com:octocat\/Spoon-Knife.git","clone_url":"https:\/\/github.com\/octocat\/Spoon-Knife.git","svn_url":"https:\/\/github.com\/octocat\/Spoon-Knife","homepage":"","size":1407736,"stargazers_count":10033,"watchers_count":10033,"language":"HTML","has_issues":true,"has_projects":true,"has_downloads":true,"has_wiki":true,"has_pages":false,"forks_count":97021,"mirror_url":null,"archived":false,"open_issues_count":11724,"license":null,"forks":97021,"open_issues":11724,"watchers":10033,"default_branch":"master"}},"_links":{"self":{"href":"https:\/\/api.github.com\/repos\/octocat\/Spoon-Knife\/pulls\/15363"},"html":{"href":"https:\/\/github.com\/octocat\/Spoon-Knife\/pull\/15363"},"issue":{"href":"https:\/\/api.github.com\/repos\/octocat\/Spoon-Knife\/issues\/15363"},"comments":{"href":"https:\/\/api.github.com\/repos\/octocat\/Spoon-Knife\/issues\/15363\/comments"},"review_comments":{"href":"https:\/\/api.github.com\/repos\/octocat\/Spoon-Knife\/pulls\/15363\/comments"},"review_comment":{"href":"https:\/\/api.github.com\/repos\/octocat\/Spoon-Knife\/pulls\/comments{\/number}"},"commits":{"href":"https:\/\/api.github.com\/repos\/octocat\/Spoon-Knife\/pulls\/15363\/commits"},"statuses":{"href":"https:\/\/api.github.com\/repos\/octocat\/Spoon-Knife\/statuses\/5051d93e0ca7fb94b61f5faf4f98b9d59d6e9166"}},"author_association":"NONE"}