{
  "name": "0.5.x",
  "commit": {
    "sha": "35190c695974f57b9306cfe33a79291b205ba76b",
    "commit": {
      "author": {
        "name": "Miro Svrtan",
        "email": "miro@mirosvrtan.me",
        "date": "2016-05-27T09:18:31Z"
      },
      "committer": {
        "name": "Miro Svrtan",
        "email": "miro@mirosvrtan.me",
        "date": "2016-05-27T09:18:31Z"
      },
      "message": "Defining strict_types on all PHP files",
      "tree": {
        "sha": "9e1b09e64f5e0e5ae1dfd8b169651689d7497a68",
        "url": "https://api.github.com/repos/devboard/github-api-facade/git/trees/9e1b09e64f5e0e5ae1dfd8b169651689d7497a68"
      },
      "url": "https://api.github.com/repos/devboard/github-api-facade/git/commits/35190c695974f57b9306cfe33a79291b205ba76b",
      "comment_count": 0
    },
    "url": "https://api.github.com/repos/devboard/github-api-facade/commits/35190c695974f57b9306cfe33a79291b205ba76b",
    "html_url": "https://github.com/devboard/github-api-facade/commit/35190c695974f57b9306cfe33a79291b205ba76b",
    "comments_url": "https://api.github.com/repos/devboard/github-api-facade/commits/35190c695974f57b9306cfe33a79291b205ba76b/comments",
    "author": {
      "login": "msvrtan",
      "id": 1780572,
      "avatar_url": "https://avatars.githubusercontent.com/u/1780572?v=3",
      "gravatar_id": "",
      "url": "https://api.github.com/users/msvrtan",
      "html_url": "https://github.com/msvrtan",
      "followers_url": "https://api.github.com/users/msvrtan/followers",
      "following_url": "https://api.github.com/users/msvrtan/following{/other_user}",
      "gists_url": "https://api.github.com/users/msvrtan/gists{/gist_id}",
      "starred_url": "https://api.github.com/users/msvrtan/starred{/owner}{/repo}",
      "subscriptions_url": "https://api.github.com/users/msvrtan/subscriptions",
      "organizations_url": "https://api.github.com/users/msvrtan/orgs",
      "repos_url": "https://api.github.com/users/msvrtan/repos",
      "events_url": "https://api.github.com/users/msvrtan/events{/privacy}",
      "received_events_url": "https://api.github.com/users/msvrtan/received_events",
      "type": "User",
      "site_admin": false
    },
    "committer": {
      "login": "msvrtan",
      "id": 1780572,
      "avatar_url": "https://avatars.githubusercontent.com/u/1780572?v=3",
      "gravatar_id": "",
      "url": "https://api.github.com/users/msvrtan",
      "html_url": "https://github.com/msvrtan",
      "followers_url": "https://api.github.com/users/msvrtan/followers",
      "following_url": "https://api.github.com/users/msvrtan/following{/other_user}",
      "gists_url": "https://api.github.com/users/msvrtan/gists{/gist_id}",
      "starred_url": "https://api.github.com/users/msvrtan/starred{/owner}{/repo}",
      "subscriptions_url": "https://api.github.com/users/msvrtan/subscriptions",
      "organizations_url": "https://api.github.com/users/msvrtan/orgs",
      "repos_url": "https://api.github.com/users/msvrtan/repos",
      "events_url": "https://api.github.com/users/msvrtan/events{/privacy}",
      "received_events_url": "https://api.github.com/users/msvrtan/received_events",
      "type": "User",
      "site_admin": false
    },
    "parents": [
      {
        "sha": "738209fcb9c610acc8698ea62109ece3741378ec",
        "url": "https://api.github.com/repos/devboard/github-api-facade/commits/738209fcb9c610acc8698ea62109ece3741378ec",
        "html_url": "https://github.com/devboard/github-api-facade/commit/738209fcb9c610acc8698ea62109ece3741378ec"
      }
    ]
  },
  "_links": {
    "self": "https://api.github.com/repos/devboard/github-api-facade/branches/0.5.x",
    "html": "https://github.com/devboard/github-api-facade/tree/0.5.x"
  }
}
