{
    "after": "f7f97ca7403ff2ee8ca83c2241f94dcfb2630079",
    "base_ref": null,
    "before": "0000000000000000000000000000000000000000",
    "commits": [
        {
            "added": [],
            "author": {
                "email": "miro@mirosvrtan.me",
                "name": "Miro Svrtan",
                "username": "msvrtan"
            },
            "committer": {
                "email": "miro@mirosvrtan.me",
                "name": "Miro Svrtan",
                "username": "msvrtan"
            },
            "distinct": true,
            "id": "f7f97ca7403ff2ee8ca83c2241f94dcfb2630079",
            "message": "Add abstract methods to Behat resources",
            "modified": [
                "src/Resources/Behat/CleanDbTrait.php",
                "src/Resources/Behat/LoginWebTrait.php",
                "src/Resources/Behat/ScreenshotTrait.php"
            ],
            "removed": [],
            "timestamp": "2017-02-11T19:44:27+01:00",
            "tree_id": "dc3e3eb0d7f0bdc9337514ddb84f9225bf4af10b",
            "url": "https://github.com/msvrtan/devboard-core/commit/f7f97ca7403ff2ee8ca83c2241f94dcfb2630079"
        }
    ],
    "compare": "https://github.com/msvrtan/devboard-core/commit/f7f97ca7403f",
    "created": true,
    "deleted": false,
    "forced": false,
    "head_commit": {
        "added": [],
        "author": {
            "email": "miro@mirosvrtan.me",
            "name": "Miro Svrtan",
            "username": "msvrtan"
        },
        "committer": {
            "email": "miro@mirosvrtan.me",
            "name": "Miro Svrtan",
            "username": "msvrtan"
        },
        "distinct": true,
        "id": "f7f97ca7403ff2ee8ca83c2241f94dcfb2630079",
        "message": "Add abstract methods to Behat resources",
        "modified": [
            "src/Resources/Behat/CleanDbTrait.php",
            "src/Resources/Behat/LoginWebTrait.php",
            "src/Resources/Behat/ScreenshotTrait.php"
        ],
        "removed": [],
        "timestamp": "2017-02-11T19:44:27+01:00",
        "tree_id": "dc3e3eb0d7f0bdc9337514ddb84f9225bf4af10b",
        "url": "https://github.com/msvrtan/devboard-core/commit/f7f97ca7403ff2ee8ca83c2241f94dcfb2630079"
    },
    "pusher": {
        "email": "msvrtan@users.noreply.github.com",
        "name": "msvrtan"
    },
    "ref": "refs/heads/03-additional-fixes",
    "repository": {
        "archive_url": "https://api.github.com/repos/msvrtan/devboard-core/{archive_format}{/ref}",
        "assignees_url": "https://api.github.com/repos/msvrtan/devboard-core/assignees{/user}",
        "blobs_url": "https://api.github.com/repos/msvrtan/devboard-core/git/blobs{/sha}",
        "branches_url": "https://api.github.com/repos/msvrtan/devboard-core/branches{/branch}",
        "clone_url": "https://github.com/msvrtan/devboard-core.git",
        "collaborators_url": "https://api.github.com/repos/msvrtan/devboard-core/collaborators{/collaborator}",
        "comments_url": "https://api.github.com/repos/msvrtan/devboard-core/comments{/number}",
        "commits_url": "https://api.github.com/repos/msvrtan/devboard-core/commits{/sha}",
        "compare_url": "https://api.github.com/repos/msvrtan/devboard-core/compare/{base}...{head}",
        "contents_url": "https://api.github.com/repos/msvrtan/devboard-core/contents/{+path}",
        "contributors_url": "https://api.github.com/repos/msvrtan/devboard-core/contributors",
        "created_at": 1462620791,
        "default_branch": "master",
        "deployments_url": "https://api.github.com/repos/msvrtan/devboard-core/deployments",
        "description": null,
        "downloads_url": "https://api.github.com/repos/msvrtan/devboard-core/downloads",
        "events_url": "https://api.github.com/repos/msvrtan/devboard-core/events",
        "fork": true,
        "forks": 0,
        "forks_count": 0,
        "forks_url": "https://api.github.com/repos/msvrtan/devboard-core/forks",
        "full_name": "msvrtan/devboard-core",
        "git_commits_url": "https://api.github.com/repos/msvrtan/devboard-core/git/commits{/sha}",
        "git_refs_url": "https://api.github.com/repos/msvrtan/devboard-core/git/refs{/sha}",
        "git_tags_url": "https://api.github.com/repos/msvrtan/devboard-core/git/tags{/sha}",
        "git_url": "git://github.com/msvrtan/devboard-core.git",
        "has_downloads": true,
        "has_issues": false,
        "has_pages": false,
        "has_wiki": true,
        "homepage": null,
        "hooks_url": "https://api.github.com/repos/msvrtan/devboard-core/hooks",
        "html_url": "https://github.com/msvrtan/devboard-core",
        "id": 58263202,
        "issue_comment_url": "https://api.github.com/repos/msvrtan/devboard-core/issues/comments{/number}",
        "issue_events_url": "https://api.github.com/repos/msvrtan/devboard-core/issues/events{/number}",
        "issues_url": "https://api.github.com/repos/msvrtan/devboard-core/issues{/number}",
        "keys_url": "https://api.github.com/repos/msvrtan/devboard-core/keys{/key_id}",
        "labels_url": "https://api.github.com/repos/msvrtan/devboard-core/labels{/name}",
        "language": "PHP",
        "languages_url": "https://api.github.com/repos/msvrtan/devboard-core/languages",
        "master_branch": "master",
        "merges_url": "https://api.github.com/repos/msvrtan/devboard-core/merges",
        "milestones_url": "https://api.github.com/repos/msvrtan/devboard-core/milestones{/number}",
        "mirror_url": null,
        "name": "devboard-core",
        "notifications_url": "https://api.github.com/repos/msvrtan/devboard-core/notifications{?since,all,participating}",
        "open_issues": 0,
        "open_issues_count": 0,
        "owner": {
            "email": "msvrtan@users.noreply.github.com",
            "name": "msvrtan"
        },
        "private": false,
        "pulls_url": "https://api.github.com/repos/msvrtan/devboard-core/pulls{/number}",
        "pushed_at": 1486838677,
        "releases_url": "https://api.github.com/repos/msvrtan/devboard-core/releases{/id}",
        "size": 2158,
        "ssh_url": "git@github.com:msvrtan/devboard-core.git",
        "stargazers": 0,
        "stargazers_count": 0,
        "stargazers_url": "https://api.github.com/repos/msvrtan/devboard-core/stargazers",
        "statuses_url": "https://api.github.com/repos/msvrtan/devboard-core/statuses/{sha}",
        "subscribers_url": "https://api.github.com/repos/msvrtan/devboard-core/subscribers",
        "subscription_url": "https://api.github.com/repos/msvrtan/devboard-core/subscription",
        "svn_url": "https://github.com/msvrtan/devboard-core",
        "tags_url": "https://api.github.com/repos/msvrtan/devboard-core/tags",
        "teams_url": "https://api.github.com/repos/msvrtan/devboard-core/teams",
        "trees_url": "https://api.github.com/repos/msvrtan/devboard-core/git/trees{/sha}",
        "updated_at": "2016-05-07T11:40:17Z",
        "url": "https://github.com/msvrtan/devboard-core",
        "watchers": 0,
        "watchers_count": 0
    },
    "sender": {
        "avatar_url": "https://avatars.githubusercontent.com/u/1780572?v=3",
        "events_url": "https://api.github.com/users/msvrtan/events{/privacy}",
        "followers_url": "https://api.github.com/users/msvrtan/followers",
        "following_url": "https://api.github.com/users/msvrtan/following{/other_user}",
        "gists_url": "https://api.github.com/users/msvrtan/gists{/gist_id}",
        "gravatar_id": "",
        "html_url": "https://github.com/msvrtan",
        "id": 1780572,
        "login": "msvrtan",
        "organizations_url": "https://api.github.com/users/msvrtan/orgs",
        "received_events_url": "https://api.github.com/users/msvrtan/received_events",
        "repos_url": "https://api.github.com/users/msvrtan/repos",
        "site_admin": false,
        "starred_url": "https://api.github.com/users/msvrtan/starred{/owner}{/repo}",
        "subscriptions_url": "https://api.github.com/users/msvrtan/subscriptions",
        "type": "User",
        "url": "https://api.github.com/users/msvrtan"
    }
}
